sl10n/__init__.py
sl10n/core.py
sl10n/locale.py
sl10n/modifiers.py
sl10n/process.py
sl10n/py.typed
sl10n/warnings.py
sl10n/pimpl/__init__.py
sl10n/pimpl/base.py
sl10n/pimpl/jsonp.py
sl10n-0.3.0.0.dist-info/LICENSE
sl10n-0.3.0.0.dist-info/METADATA
sl10n-0.3.0.0.dist-info/WHEEL
sl10n-0.3.0.0.dist-info/top_level.txt
sl10n-0.3.0.0.dist-info/RECORD
