Metadata-Version: 2.1
Name: sl10n
Version: 0.3.0.0
Summary: Static localization system that reduces the headache of working with localization
Author: SyberiaK
License: MIT License
Project-URL: Homepage, https://github.com/SyberiaK/sl10n
Project-URL: Documentation, https://syberiak.github.io/sl10n
Project-URL: Issues, https://github.com/SyberiaK/sl10n/issues
Classifier: Development Status :: 3 - Alpha
Classifier: Intended Audience :: Developers
Classifier: License :: OSI Approved :: MIT License
Classifier: Operating System :: OS Independent
Classifier: Programming Language :: Python :: 3.8
Classifier: Programming Language :: Python :: 3.9
Classifier: Programming Language :: Python :: 3.10
Classifier: Programming Language :: Python :: 3.11
Classifier: Programming Language :: Python :: 3.12
Classifier: Topic :: Software Development
Classifier: Topic :: Software Development :: Internationalization
Classifier: Topic :: Software Development :: Localization
Classifier: Topic :: Text Processing :: Linguistic
Classifier: Typing :: Typed
Requires-Python: >=3.8
License-File: LICENSE
Provides-Extra: docs
Requires-Dist: mkdocs >=1.5.3 ; extra == 'docs'
Requires-Dist: mkdocstrings >=0.22.0 ; extra == 'docs'
Requires-Dist: mkdocstrings-python >=1.6.0 ; extra == 'docs'
Requires-Dist: mkdocs-gen-files >=0.5.0 ; extra == 'docs'
Requires-Dist: mkdocs-literate-nav >=0.6.0 ; extra == 'docs'
Requires-Dist: mkdocs-material >=9.5.5 ; extra == 'docs'
Requires-Dist: mkdocs-git-revision-date-localized-plugin >=1.2.0 ; extra == 'docs'
Requires-Dist: black >=23.12.1 ; extra == 'docs'
Provides-Extra: test
Requires-Dist: orjson >=3.9.5 ; extra == 'test'
Requires-Dist: pytest >=7.4.0 ; extra == 'test'
Requires-Dist: pytest-cov >=4.1.0 ; extra == 'test'
Requires-Dist: pythom-rapidjson >=1.10 ; extra == 'test'
Requires-Dist: simplejson >=3.19.1 ; extra == 'test'
Requires-Dist: ujson >=5.8.0 ; extra == 'test'
